Workbook

Sheet Dashboard
A1: BUDGET TRACKER — DASHBOARD
A2: Data auto-populated from the "Summary" sheet. Register transactions in the Monthly Log.
A4: Total Income | E4: Total Budgeted | I4: Total Spent | M4: Remaining
A5: =Summary!C3 | E5: =Summary!C5 | I5: =Summary!C7 | M5: =Summary!C9
A8: HOUSE LOAN | J8: INSURANCES
A9: Mortgage payment | B9: Amortisation | C9: HOA / Bostadsrättsavgift | D9: Home insurance (building) | E9: Electricity | F9: Internet | J9: Health insurance | K9: Car insurance | L9: Life insurance | M9: Pet insurance
A10: ='House Loan'!E4 | B10: ='House Loan'!E5 | C10: ='House Loan'!E6 | D10: ='House Loan'!E7 | E10: ='House Loan'!E8 | F10: ='House Loan'!E9 | J10: ='Insurances'!E4 | K10: ='Insurances'!E5 | L10: ='Insurances'!E6 | M10: ='Insurances'!E7
A23: Budget: | B23: =Summary!C12 | D23: Spent: | E23: =Summary!D12 | G23: Used: | H23: =IFERROR(Summary!D12/Summary!C12, 0) | J23: Budget: | K23: =Summary!C14 | M23: Spent: | N23: =Summary!D14 | P23: Used: | Q23: =IFERROR(Summary!D14/Summary!C14, 0)
A36: SUBSCRIPTIONS | J36: SAVINGS
A37: Spotify | B37: Netflix | C37: Cloud storage | D37: Gym membership | E37: News / magazine | J37: Emergency fund | K37: Investment account | L37: Vacation fund | M37: Retirement (extra)
A38: ='Subscriptions'!E4 | B38: ='Subscriptions'!E5 | C38: ='Subscriptions'!E6 | D38: ='Subscriptions'!E7 | E38: ='Subscriptions'!E8 | J38: ='Savings'!E4 | K38: ='Savings'!E5 | L38: ='Savings'!E6 | M38: ='Savings'!E7
A51: Budget: | B51: =Summary!C16 | D51: Spent: | E51: =Summary!D16 | G51: Used: | H51: =IFERROR(Summary!D16/Summary!C16, 0) | J51: Budget: | K51: =Summary!C18 | M51: Spent: | N51: =Summary!D18 | P51: Used: | Q51: =IFERROR(Summary!D18/Summary!C18, 0)
A64: MISC.
A65: Groceries | B65: Going out meals | C65: Transportation | D65: Clothing | E65: Entertainment | F65: Personal care | G65: Gifts
A66: ='Misc.'!E4 | B66: ='Misc.'!E5 | C66: ='Misc.'!E6 | D66: ='Misc.'!E7 | E66: ='Misc.'!E8 | F66: ='Misc.'!E9 | G66: ='Misc.'!E10
A79: Budget: | B79: =Summary!C20 | D79: Spent: | E79: =Summary!D20 | G79: Used: | H79: =IFERROR(Summary!D20/Summary!C20, 0)

Sheet Monthly Log
A1: MONTHLY TRANSACTION LOG
A2: Date | B2: Category | C2: Item | D2: Amount (SEK) | E2: Note
A3: 2026-03-01 | B3: Misc. | C3: Groceries – ICA | D3: 850 | E3: Weekly shop
A4: 2026-03-03 | B4: Misc. | C4: Going out meals – lunch | D4: 145
A5: 2026-03-05 | B5: Subscriptions | C5: Spotify | D5: 129 | E5: Monthly
A6: 2026-03-07 | B6: House Loan | C6: Electricity – Vattenfall | D6: 780 | E6: March bill
A7: 2026-03-10 | B7: Misc. | C7: Going out meals – dinner | D7: 320
A8: 2026-03-15 | B8: Savings | C8: Emergency fund | D8: 2000 | E8: Auto-transfer

Sheet Income
A1: INCOME
A2: All income sources for the month
A3: # | B3: Source | C3: Budgeted (SEK) | D3: Actual (SEK)
A4: 1 | B4: Salary (net) | C4: 35000 | D4: 35000
A5: 2 | B5: Side income | C5: 0 | D5: 0
A6: 3 | B6: Other income | C6: 0 | D6: 0
B17: TOTAL — INCOME | C17: =SUM(C4:C16) | D17: =SUM(D4:D16)

Sheet House Loan
A1: HOUSE LOAN
A2: Housing-related fixed costs
A3: # | B3: Item | C3: Budget (SEK) | D3: Spent from Log (SEK) | E3: Spent Total (SEK) | F3: Remaining (SEK) | G3: % Used
A4: 1 | B4: Mortgage payment | C4: 8500 | D4: =SUMPRODUCT(('Monthly Log'!B$3:B$509="House Loan")*(ISNUMBER(SEARCH(B4,'Monthly Log'!C$3:C$509)))*('Monthly Log'!D$3:D$509)) | E4: =D4 | F4: =C4-E4 | G4: =IFERROR(E4/C4, 0)
A5: 2 | B5: Amortisation | C5: 3000 | D5: =SUMPRODUCT(('Monthly Log'!B$3:B$509="House Loan")*(ISNUMBER(SEARCH(B5,'Monthly Log'!C$3:C$509)))*('Monthly Log'!D$3:D$509)) | E5: =D5 | F5: =C5-E5 | G5: =IFERROR(E5/C5, 0)
A6: 3 | B6: HOA / Bostadsrättsavgift | C6: 4200 | D6: =SUMPRODUCT(('Monthly Log'!B$3:B$509="House Loan")*(ISNUMBER(SEARCH(B6,'Monthly Log'!C$3:C$509)))*('Monthly Log'!D$3:D$509)) | E6: =D6 | F6: =C6-E6 | G6: =IFERROR(E6/C6, 0)
A7: 4 | B7: Home insurance (building) | C7: 350 | D7: =SUMPRODUCT(('Monthly Log'!B$3:B$509="House Loan")*(ISNUMBER(SEARCH(B7,'Monthly Log'!C$3:C$509)))*('Monthly Log'!D$3:D$509)) | E7: =D7 | F7: =C7-E7 | G7: =IFERROR(E7/C7, 0)
A8: 5 | B8: Electricity | C8: 800 | D8: =SUMPRODUCT(('Monthly Log'!B$3:B$509="House Loan")*(ISNUMBER(SEARCH(B8,'Monthly Log'!C$3:C$509)))*('Monthly Log'!D$3:D$509)) | E8: =D8 | F8: =C8-E8 | G8: =IFERROR(E8/C8, 0)
A9: 6 | B9: Internet | C9: 399 | D9: =SUMPRODUCT(('Monthly Log'!B$3:B$509="House Loan")*(ISNUMBER(SEARCH(B9,'Monthly Log'!C$3:C$509)))*('Monthly Log'!D$3:D$509)) | E9: =D9 | F9: =C9-E9 | G9: =IFERROR(E9/C9, 0)
B20: TOTAL — HOUSE LOAN | C20: =SUM(C4:C19) | D20: =SUM(D4:D19) | E20: =SUM(E4:E19) | F20: =C20-E20 | G20: =IFERROR(E20/C20, 0)

Sheet Insurances
A1: INSURANCES
A2: Monthly insurance premiums
A3: # | B3: Item | C3: Budget (SEK) | D3: Spent from Log (SEK) | E3: Spent Total (SEK) | F3: Remaining (SEK) | G3: % Used
A4: 1 | B4: Health insurance | C4: 450 | D4: =SUMPRODUCT(('Monthly Log'!B$3:B$509="Insurances")*(ISNUMBER(SEARCH(B4,'Monthly Log'!C$3:C$509)))*('Monthly Log'!D$3:D$509)) | E4: =D4 | F4: =C4-E4 | G4: =IFERROR(E4/C4, 0)
A5: 2 | B5: Car insurance | C5: 600 | D5: =SUMPRODUCT(('Monthly Log'!B$3:B$509="Insurances")*(ISNUMBER(SEARCH(B5,'Monthly Log'!C$3:C$509)))*('Monthly Log'!D$3:D$509)) | E5: =D5 | F5: =C5-E5 | G5: =IFERROR(E5/C5, 0)
A6: 3 | B6: Life insurance | C6: 300 | D6: =SUMPRODUCT(('Monthly Log'!B$3:B$509="Insurances")*(ISNUMBER(SEARCH(B6,'Monthly Log'!C$3:C$509)))*('Monthly Log'!D$3:D$509)) | E6: =D6 | F6: =C6-E6 | G6: =IFERROR(E6/C6, 0)
A7: 4 | B7: Pet insurance | C7: 250 | D7: =SUMPRODUCT(('Monthly Log'!B$3:B$509="Insurances")*(ISNUMBER(SEARCH(B7,'Monthly Log'!C$3:C$509)))*('Monthly Log'!D$3:D$509)) | E7: =D7 | F7: =C7-E7 | G7: =IFERROR(E7/C7, 0)
B18: TOTAL — INSURANCES | C18: =SUM(C4:C17) | D18: =SUM(D4:D17) | E18: =SUM(E4:E17) | F18: =C18-E18 | G18: =IFERROR(E18/C18, 0)

Sheet Subscriptions
A1: SUBSCRIPTIONS
A2: Recurring subscription services
A3: # | B3: Item | C3: Budget (SEK) | D3: Spent from Log (SEK) | E3: Spent Total (SEK) | F3: Remaining (SEK) | G3: % Used
A4: 1 | B4: Spotify | C4: 129 | D4: =SUMPRODUCT(('Monthly Log'!B$3:B$509="Subscriptions")*(ISNUMBER(SEARCH(B4,'Monthly Log'!C$3:C$509)))*('Monthly Log'!D$3:D$509)) | E4: =D4 | F4: =C4-E4 | G4: =IFERROR(E4/C4, 0)
A5: 2 | B5: Netflix | C5: 169 | D5: =SUMPRODUCT(('Monthly Log'!B$3:B$509="Subscriptions")*(ISNUMBER(SEARCH(B5,'Monthly Log'!C$3:C$509)))*('Monthly Log'!D$3:D$509)) | E5: =D5 | F5: =C5-E5 | G5: =IFERROR(E5/C5, 0)
A6: 3 | B6: Cloud storage | C6: 99 | D6: =SUMPRODUCT(('Monthly Log'!B$3:B$509="Subscriptions")*(ISNUMBER(SEARCH(B6,'Monthly Log'!C$3:C$509)))*('Monthly Log'!D$3:D$509)) | E6: =D6 | F6: =C6-E6 | G6: =IFERROR(E6/C6, 0)
A7: 4 | B7: Gym membership | C7: 399 | D7: =SUMPRODUCT(('Monthly Log'!B$3:B$509="Subscriptions")*(ISNUMBER(SEARCH(B7,'Monthly Log'!C$3:C$509)))*('Monthly Log'!D$3:D$509)) | E7: =D7 | F7: =C7-E7 | G7: =IFERROR(E7/C7, 0)
A8: 5 | B8: News / magazine | C8: 149 | D8: =SUMPRODUCT(('Monthly Log'!B$3:B$509="Subscriptions")*(ISNUMBER(SEARCH(B8,'Monthly Log'!C$3:C$509)))*('Monthly Log'!D$3:D$509)) | E8: =D8 | F8: =C8-E8 | G8: =IFERROR(E8/C8, 0)
B19: TOTAL — SUBSCRIPTIONS | C19: =SUM(C4:C18) | D19: =SUM(D4:D18) | E19: =SUM(E4:E18) | F19: =C19-E19 | G19: =IFERROR(E19/C19, 0)

Sheet Savings
A1: SAVINGS
A2: Savings goals & transfers
A3: # | B3: Item | C3: Budget (SEK) | D3: Spent from Log (SEK) | E3: Spent Total (SEK) | F3: Remaining (SEK) | G3: % Used
A4: 1 | B4: Emergency fund | C4: 2000 | D4: =SUMPRODUCT(('Monthly Log'!B$3:B$509="Savings")*(ISNUMBER(SEARCH(B4,'Monthly Log'!C$3:C$509)))*('Monthly Log'!D$3:D$509)) | E4: =D4 | F4: =C4-E4 | G4: =IFERROR(E4/C4, 0)
A5: 2 | B5: Investment account | C5: 3000 | D5: =SUMPRODUCT(('Monthly Log'!B$3:B$509="Savings")*(ISNUMBER(SEARCH(B5,'Monthly Log'!C$3:C$509)))*('Monthly Log'!D$3:D$509)) | E5: =D5 | F5: =C5-E5 | G5: =IFERROR(E5/C5, 0)
A6: 3 | B6: Vacation fund | C6: 1000 | D6: =SUMPRODUCT(('Monthly Log'!B$3:B$509="Savings")*(ISNUMBER(SEARCH(B6,'Monthly Log'!C$3:C$509)))*('Monthly Log'!D$3:D$509)) | E6: =D6 | F6: =C6-E6 | G6: =IFERROR(E6/C6, 0)
A7: 4 | B7: Retirement (extra) | C7: 1500 | D7: =SUMPRODUCT(('Monthly Log'!B$3:B$509="Savings")*(ISNUMBER(SEARCH(B7,'Monthly Log'!C$3:C$509)))*('Monthly Log'!D$3:D$509)) | E7: =D7 | F7: =C7-E7 | G7: =IFERROR(E7/C7, 0)
B18: TOTAL — SAVINGS | C18: =SUM(C4:C17) | D18: =SUM(D4:D17) | E18: =SUM(E4:E17) | F18: =C18-E18 | G18: =IFERROR(E18/C18, 0)

Sheet Misc.
A1: MISC.
A2: Variable & discretionary spending
A3: # | B3: Item | C3: Budget (SEK) | D3: Spent from Log (SEK) | E3: Spent Total (SEK) | F3: Remaining (SEK) | G3: % Used
A4: 1 | B4: Groceries | C4: 5000 | D4: =SUMPRODUCT(('Monthly Log'!B$3:B$509="Misc.")*(ISNUMBER(SEARCH(B4,'Monthly Log'!C$3:C$509)))*('Monthly Log'!D$3:D$509)) | E4: =D4 | F4: =C4-E4 | G4: =IFERROR(E4/C4, 0)
A5: 2 | B5: Going out meals | C5: 1000 | D5: =SUMPRODUCT(('Monthly Log'!B$3:B$509="Misc.")*(ISNUMBER(SEARCH(B5,'Monthly Log'!C$3:C$509)))*('Monthly Log'!D$3:D$509)) | E5: =D5 | F5: =C5-E5 | G5: =IFERROR(E5/C5, 0)
A6: 3 | B6: Transportation | C6: 1200 | D6: =SUMPRODUCT(('Monthly Log'!B$3:B$509="Misc.")*(ISNUMBER(SEARCH(B6,'Monthly Log'!C$3:C$509)))*('Monthly Log'!D$3:D$509)) | E6: =D6 | F6: =C6-E6 | G6: =IFERROR(E6/C6, 0)
A7: 4 | B7: Clothing | C7: 500 | D7: =SUMPRODUCT(('Monthly Log'!B$3:B$509="Misc.")*(ISNUMBER(SEARCH(B7,'Monthly Log'!C$3:C$509)))*('Monthly Log'!D$3:D$509)) | E7: =D7 | F7: =C7-E7 | G7: =IFERROR(E7/C7, 0)
A8: 5 | B8: Entertainment | C8: 500 | D8: =SUMPRODUCT(('Monthly Log'!B$3:B$509="Misc.")*(ISNUMBER(SEARCH(B8,'Monthly Log'!C$3:C$509)))*('Monthly Log'!D$3:D$509)) | E8: =D8 | F8: =C8-E8 | G8: =IFERROR(E8/C8, 0)
A9: 6 | B9: Personal care | C9: 300 | D9: =SUMPRODUCT(('Monthly Log'!B$3:B$509="Misc.")*(ISNUMBER(SEARCH(B9,'Monthly Log'!C$3:C$509)))*('Monthly Log'!D$3:D$509)) | E9: =D9 | F9: =C9-E9 | G9: =IFERROR(E9/C9, 0)
A10: 7 | B10: Gifts | C10: 300 | D10: =SUMPRODUCT(('Monthly Log'!B$3:B$509="Misc.")*(ISNUMBER(SEARCH(B10,'Monthly Log'!C$3:C$509)))*('Monthly Log'!D$3:D$509)) | E10: =D10 | F10: =C10-E10 | G10: =IFERROR(E10/C10, 0)
B21: TOTAL — MISC. | C21: =SUM(C4:C20) | D21: =SUM(D4:D20) | E21: =SUM(E4:E20) | F21: =C21-E21 | G21: =IFERROR(E21/C21, 0)

Sheet Summary
A1: BUDGET SUMMARY
B3: Total Monthly Income | C3: ='Income'!D17
B5: Total Budgeted Expenses | C5: ='House Loan'!C20+'Insurances'!C18+'Subscriptions'!C19+'Savings'!C18+'Misc.'!C21
B7: Total Spent (Actual) | C7: ='House Loan'!E20+'Insurances'!E18+'Subscriptions'!E19+'Savings'!E18+'Misc.'!E21
B9: Remaining (Income − Spent) | C9: =C3-C7
B11: Category | C11: Budgeted | D11: Spent | E11: Remaining | F11: % Used
B12: House Loan | C12: ='House Loan'!C20 | D12: ='House Loan'!E20 | E12: =C12-D12 | F12: =IFERROR(D12/C12, 0)
B14: Insurances | C14: ='Insurances'!C18 | D14: ='Insurances'!E18 | E14: =C14-D14 | F14: =IFERROR(D14/C14, 0)
B16: Subscriptions | C16: ='Subscriptions'!C19 | D16: ='Subscriptions'!E19 | E16: =C16-D16 | F16: =IFERROR(D16/C16, 0)
B18: Savings | C18: ='Savings'!C18 | D18: ='Savings'!E18 | E18: =C18-D18 | F18: =IFERROR(D18/C18, 0)
B20: Misc. | C20: ='Misc.'!C21 | D20: ='Misc.'!E21 | E20: =C20-D20 | F20: =IFERROR(D20/C20, 0)
B24: Category | C24: Budgeted | D24: Spent
B25: House Loan | C25: =C12 | D25: =D12
B26: Insurances | C26: =C14 | D26: =D14
B27: Subscriptions | C27: =C16 | D27: =D16
B28: Savings | C28: =C18 | D28: =D18
B29: Misc. | C29: =C20 | D29: =D20

Sheet How to Use
A1: HOW TO USE THIS BUDGET TRACKER
B3: 1. Record transactions
B4: Go to the 'Monthly Log' sheet. Enter the date, select a category from the dropdown, type the item name (include the budget item keyword, e.g. 'Going out meals – lunch'), enter the amount in SEK, and optionally add a note.
B6: 2. Automatic aggregation
B7: Each category sheet (House Loan, Insurances, etc.) uses SUMPRODUCT formulas to automatically pull spending from the Monthly Log. The 'Spent from Log' column searches for the item name in your transaction descriptions.
B9: 3. Dashboard charts
B10: The Dashboard shows donut charts for each category. As you spend, the 'Spent' segment fills up — like a loading wheel. Green = under budget, filling up = caution.
B12: 4. Summary overview
B13: The Summary sheet shows total income vs total expenses, with a bar chart comparison. The 'Remaining' value shows how much of your income is unallocated after spending.
B15: 5. Adding new budget items
B16: Each category sheet has 10 blank rows below the pre-filled items. Simply type a new item name and budget amount. The formulas will extend automatically. Then use the same item name keyword when logging transactions.
B18: 6. Adjusting budgets
B19: Change any budget amount in column C of any category sheet. All totals and charts update automatically via formulas.
... B25: Upload this .xlsx file to Google Drive, then open with Google Sheets. All formulas, charts, and formatting are compatible.
